qtoggleserver/zigbee2mqtt/__init__.py
qtoggleserver/zigbee2mqtt/client.py
qtoggleserver/zigbee2mqtt/exceptions.py
qtoggleserver/zigbee2mqtt/ports.py
qtoggleserver_zigbee2mqtt-1.9.3.dist-info/licenses/LICENSE.txt
qtoggleserver_zigbee2mqtt-1.9.3.dist-info/METADATA
qtoggleserver_zigbee2mqtt-1.9.3.dist-info/WHEEL
qtoggleserver_zigbee2mqtt-1.9.3.dist-info/top_level.txt
qtoggleserver_zigbee2mqtt-1.9.3.dist-info/RECORD
