Metadata-Version: 2.4
Name: qtoggleserver-zigbee2mqtt
Version: 1.9.3
Summary: qToggleServer integration with Zigbee2MQTT
Author-email: Calin Crisan <ccrisan@gmail.com>
License: Apache 2.0
Requires-Python: >=3.11
License-File: LICENSE.txt
Requires-Dist: aiomqtt
Dynamic: license-file
